ailia_tflite/LICENSE_AILIA_EN.pdf
ailia_tflite/LICENSE_AILIA_JA.pdf
ailia_tflite/__init__.py
ailia_tflite/license.py
ailia_tflite/linux/arm64-v8a/libailia_tflite.so
ailia_tflite/linux/x64/libailia_tflite.so
ailia_tflite/linux/x64/libiomp5.so
ailia_tflite/mac/libailia_tflite.dylib
ailia_tflite/oss/LICENSE_INTELMKL.txt
ailia_tflite/oss/LICENSE_TENSORFLOW.txt
ailia_tflite/windows/x64/ailia_tflite.dll
ailia_tflite/windows/x64/libiomp5md.dll
ailia_tflite-1.2.4.0.data/scripts/__init__.py
ailia_tflite-1.2.4.0.data/scripts/license.py
ailia_tflite-1.2.4.0.dist-info/METADATA
ailia_tflite-1.2.4.0.dist-info/WHEEL
ailia_tflite-1.2.4.0.dist-info/top_level.txt
ailia_tflite-1.2.4.0.dist-info/RECORD
