Metadata-Version: 2.4
Name: ailia_tflite
Version: 1.2.4.0
Summary: ailia TFLite Runtime
Home-page: https://ailia.jp/
Author: ailia Inc.
Author-email: contact@ailia.ai
License: https://ailia.ai/license/en/
Requires-Python: >3.6
Dynamic: author
Dynamic: author-email
Dynamic: description
Dynamic: description-content-type
Dynamic: home-page
Dynamic: license
Dynamic: requires-python
Dynamic: summary
